{
    "version": "https://jsonfeed.org/version/1",
    "title": "新浪新闻",
    "home_page_url": "https://coolseaman.github.io/sina-news/",
    "feed_url": "https://coolseaman.github.io/sina-news/rss.json",
    "description": "新浪全球实时财经新闻直播",
    "items": [
        {
            "id": 2685530,
            "content_html": "",
            "url": "https://finance.sina.cn/7x24/2022-05-27/detail-imizirau5026316.d.html",
            "title": "【生猪概念股冷期热 左侧右侧交易各藏玄机】“从4月中旬起，生猪期货价格震荡反弹，但生猪概念相关的股票价格却下来了。”在股票、期货市场均有持仓的投资者鲁先生告诉记者，他并没有平仓，反而加仓了生猪概念股，当前正是“捡便宜”的好时机。目前，多数市场人士认为本轮“猪周期”已经启动或启动在即，但对后市行情演变节奏存在明显分歧。部分分析师建议，投资者可在股票市场进行右侧交易等待新周期兑现，或在期货市场以“向现货回归”的思路进行左侧交易。（中国证券报）",
            "date_modified": "2022-05-26T23:12:48.000Z"
        },
        {
            "id": 2685529,
            "content_html": "",
            "url": "https://finance.sina.cn/7x24/2022-05-27/detail-imizmscu3613544.d.html",
            "title": "【云南景东县新增本土确诊病例1例】云南发布消息，5月26日0-24时，全省新增确诊病例3例，其中境外输入2例（老挝、缅甸各1例），本土1例（景东）。全省新增无症状感染者1例，为境外输入（缅甸）。解除医学观察6例，尚在医学观察27例（境外输入23例）。",
            "date_modified": "2022-05-26T23:10:36.000Z"
        },
        {
            "id": 2685528,
            "content_html": "",
            "url": "https://finance.sina.cn/7x24/2022-05-27/detail-imizmscu3613469.d.html",
            "title": "【乌副防长：顿巴斯地区战斗已达最高烈度】据俄罗斯媒体报道，当地时间26日晚（北京时间27日凌晨），乌克兰总统办公室主任顾问阿列斯托维奇证实，乌克兰军队丢掉了顿涅茨克的战略要地——红利曼。卢甘斯克军事行政长官则证实，俄军已占领卢甘斯克95%的领土。乌克兰国防部副部长马里亚尔表示，顿巴斯地区的战斗已经达到“最高烈度”。（央视新闻）",
            "date_modified": "2022-05-26T23:10:12.000Z"
        },
        {
            "id": 2685527,
            "content_html": "",
            "url": "https://finance.sina.cn/7x24/2022-05-27/detail-imizmscu3613402.d.html",
            "title": "据郑州发布：27日起，郑州地铁5号线全线车站恢复运营服务。",
            "date_modified": "2022-05-26T23:09:56.000Z"
        },
        {
            "id": 2685526,
            "content_html": "",
            "url": "https://finance.sina.cn/7x24/2022-05-27/detail-imizirau5025890.d.html",
            "title": "【触及下修条款个券增多 可转债博弈机会显现】在今年A股市场持续震荡的大背景下，触发转股价格下修条款的可转债数量增多，转股价格下修的博弈机会逐渐引起市场参与者关注。业内人士分析，转股价格下修可迅速提升转股价值，影响可转债市场价格，由此产生交易性机会。不过，发行人会否以及在多大程度上调整转股价，取决于其对促进转股、稀释股权等因素的综合考量，存在一定的不确定性，投资者在参与时应认真选择标的。（中国证券报）",
            "date_modified": "2022-05-26T23:09:36.000Z"
        },
        {
            "id": 2685524,
            "content_html": "",
            "url": "https://finance.sina.cn/7x24/2022-05-27/detail-imizirau5025525.d.html",
            "title": "【山东新增本土无症状感染者3例】健康山东官微消息，5月26日0时至24时，全省报告无新增本土确诊病例。新增本土无症状感染者3例（其中，5月24日1人从省外乘坐G262次列车抵达济南西站、1人从省外乘坐G54次列车抵达济南西站，5月25日1人从省外乘坐D733次列车抵达菏泽站。上述人员抵达后均闭环转运至集中隔离点，隔离期间检测发现）。无新增境外输入确诊病例。新增境外输入无症状感染者1例，在济南，为德国输入。",
            "date_modified": "2022-05-26T23:06:44.000Z"
        },
        {
            "id": 2685523,
            "content_html": "",
            "url": "https://finance.sina.cn/7x24/2022-05-27/detail-imizirau5025478.d.html",
            "title": "【海外资管众大佬参与QFLP和QDLP试点】近期，贝莱德基金、安中投资、集富亚洲等多家海外资管机构参与合格境外有限合伙人（QFLP）和合格境内有限合伙人（QDLP）试点，对中国市场加码投资。外资机构坚定布局中国市场的信心，源自于中国资管业务广阔的市场前景，以及出色的历史回报。外资机构普遍表示，中国市场对国际资管机构而言不可或缺，短期波动难以撼动长期布局信心，期待中国业务继续为其带来超额收益。",
            "date_modified": "2022-05-26T23:06:20.000Z"
        },
        {
            "id": 2685522,
            "content_html": "",
            "url": "https://finance.sina.cn/7x24/2022-05-27/detail-imizmscu3612866.d.html",
            "title": "【3M因污染被罚款280万美元】美国3M公司将支付280万美元的罚款，此前明尼苏达州监管机构发现其一座焚烧厂存在一系列危险废物违规行为，该焚烧厂已被关闭。",
            "date_modified": "2022-05-26T23:05:28.000Z"
        },
        {
            "id": 2685520,
            "content_html": "",
            "url": "https://finance.sina.cn/7x24/2022-05-27/detail-imizmscu3612068.d.html",
            "title": "【5月27日(周五)交易日待公布重点数据及财经事件提醒】1) 07:30 日本5月东京CPI年率2) 09:30 中国4月规模以上工业企业利润年率3) 16:00 欧元区4月M3广义货币4) 20:30 美国4月个人支出月率和批发库存月率初值5) 20:30 美国4月PCE物价指数年率6) 22:00 美国5月密歇根大学消费者信心指数终值7) 次日01:00 美国截至5月27日当周石油钻井总数8) 次日03:30 美国商品期货交易委员会（CFTC）公布周度持仓报告。",
            "date_modified": "2022-05-26T22:59:01.000Z"
        },
        {
            "id": 2685519,
            "content_html": "",
            "url": "https://finance.sina.cn/7x24/2022-05-27/detail-imizmscu3611794.d.html",
            "title": "【恒大：以13.5亿元人民币转让宁波地产项目，预计此次出售将带来约1.75亿元人民币收益】中国恒大集团港交所公告称，同意以13.5亿元人民币（2亿美元）的价格转让宁波的一个房地产项目。项目是城市之光广场，买方是浙江省国资委为实际控制人的浙建房产和浙江省建设投资集团为实际控制人的浙江建工。部分对价将用于直接抵偿恒大就其在宁波市的其他项目欠付浙江建工及其子公司的2.186亿元人民币未付工程款，约2.94亿元人民币的部分出售款项将用作化解恒大就项目地块的若干未付工程款及恒大在宁波市其他项目欠付浙江建工及其子公司的未付工程款，其余所得款项将用作一般营运资金。恒大预计此次出售将带来约1.75亿元人民币的收益。",
            "date_modified": "2022-05-26T22:56:31.000Z"
        },
        {
            "id": 2685518,
            "content_html": "",
            "url": "https://finance.sina.cn/7x24/2022-05-27/detail-imizirau5023718.d.html",
            "title": "  【A股市场韧性凸显，三大掘金主线浮现】 近一个月以来，大盘累计反弹逾8%。分析人士认为，随着新冠肺炎疫情形势持续改善以及宏观政策持续发力，A股短期仍具备反弹空间。东方证券策略分析师薛俊认为，行业板块和主题投资板块轮动将会是A股全年“主旋律”，建议关注以下三条主线：一是“稳增长”“宽信用”相关的地产链、基建链和大金融板块；二是复工复产和大消费主线；三是A股市场上与美债长端利率负相关性较强、基本面稳健的军工板块。（中证报）",
            "date_modified": "2022-05-26T22:52:48.000Z"
        },
        {
            "id": 2685517,
            "content_html": "",
            "url": "https://finance.sina.cn/7x24/2022-05-27/detail-imizirau5023180.d.html",
            "title": "【4月中国债券市场发行超5万亿元】中国人民银行发布的最新数据显示，4月份，我国债券市场共发行各类债券50512亿元。其中，国债发行7656.3亿元，地方政府债券发行2842.1亿元，金融债券发行7693.2亿元，公司信用类债券发行13617.4亿元，信贷资产支持证券发行272.3亿元，同业存单发行18022.4亿元。至4月末，境外机构在中国债券市场的托管余额为3.9万亿元，占中国债券市场托管余额的比重为2.8%。",
            "date_modified": "2022-05-26T22:46:58.000Z"
        },
        {
            "id": 2685516,
            "content_html": "",
            "url": "https://finance.sina.cn/7x24/2022-05-27/detail-imizirau5023103.d.html",
            "title": "日本考虑发行桥梁债券为国防开支提供资金。",
            "date_modified": "2022-05-26T22:46:04.000Z"
        },
        {
            "id": 2685515,
            "content_html": "",
            "url": "https://finance.sina.cn/7x24/2022-05-27/detail-imizirau5022815.d.html",
            "title": "日本央行将开始探索自身的气候变化措施。",
            "date_modified": "2022-05-26T22:43:19.000Z"
        },
        {
            "id": 2685514,
            "content_html": "",
            "url": "https://finance.sina.cn/7x24/2022-05-27/detail-imizmscu3610252.d.html",
            "title": "【俄对外情报局：美国招募训练极端分子派往乌克兰】俄罗斯对外情报局近日发表声明说，美国积极招募包括隶属于极端组织在内的极端分子以雇佣兵身份参加在乌克兰的战斗。今年4月，在美国情报机构的参与下，大约60名极端分子从叙利亚库尔德人控制的监狱中获释。他们随后被转至位于叙利亚的一处美军基地接受训练，以便被派往乌克兰。（央视）",
            "date_modified": "2022-05-26T22:41:12.000Z"
        },
        {
            "id": 2685513,
            "content_html": "",
            "url": "https://finance.sina.cn/7x24/2022-05-27/detail-imizirau5022491.d.html",
            "title": "日本考虑发行过渡性债券为国防提供资金。",
            "date_modified": "2022-05-26T22:40:21.000Z"
        },
        {
            "id": 2685512,
            "content_html": "",
            "url": "https://finance.sina.cn/7x24/2022-05-27/detail-imizirau5022451.d.html",
            "title": "【增强资本实力，信托业迎新一轮增资潮】2022年以来，为增强公司风险抵御能力，增强行业竞争力，多家信托公司走上增资扩股之路。日前，华宝信托有限责任公司增资项目已在北京产权交易所挂牌，该公司拟向全市场公开征集意向投资者，计划引入持股比例在5%-10%之间的新股东。据统计，今年以来，已有浙金信托、中诚信托、国通信托等信托公司先后完成了增资项目。业内人士指出，信托公司提高资本金规模是未来适应资金信托新规要求最直接的方式，也是过渡期平稳转型的需要，预计未来信托业将迎来新一轮增资潮。（中证报）",
            "date_modified": "2022-05-26T22:40:07.000Z"
        },
        {
            "id": 2685511,
            "content_html": "",
            "url": "https://finance.sina.cn/7x24/2022-05-27/detail-imizmscu3609690.d.html",
            "title": "【年内超700家公司公布回购预案，三大行业数量居前】截至5月26日，年内共有713家公司发布回购预案，二季度拟回购公司已超450家，其中4月份近350家，5月份超过105家。从行业分布来看，共有30个行业的公司发布回购预案，电子、计算机、医药生物板块公司数量居多，均超过70家；煤炭、综合、钢铁行业最少，均不足5家。从公司属性来看，回购公司中以民营企业居多，占比超七成。尚未实施回购的430家公司中，回购金额上限达到亿元，且机构预测2022年、2023年净利润增幅上限超30%的公司有19家，医药生物、汽车行业公司数量居多。（证券时报）",
            "date_modified": "2022-05-26T22:35:43.000Z"
        },
        {
            "id": 2685510,
            "content_html": "",
            "url": "https://finance.sina.cn/7x24/2022-05-27/detail-imizmscu3609655.d.html",
            "title": "【经参：发展数字经济，加快产业链自主可控】当前和今后相当长的一段时期内，充分发挥数字经济在生产要素配置中的优化与集成作用，进一步促进数字经济与实体经济的深度融合，依托数字经济推进产业链数字化转型，着力突破核心技术与关键功能部件，加快产业链强链、补链、扩链并在此基础上打通产业链与创新链，是我国畅通国内循环实现产业布局优化最迫切的问题。首先，加快数字经济发展的基础设施建设。其次，提升产业链智能制造水平。第三，努力构建工业互联网生态系统。最后，以更加自信的开放促进产业链创新。",
            "date_modified": "2022-05-26T22:35:12.000Z"
        },
        {
            "id": 2685509,
            "content_html": "",
            "title": "【多部门释放数字经济新一轮利好】2022中国国际大数据产业博览会26日在线上举行。工信部、国家发展改革委、中央网信办等部门相关负责人齐发声，释放政策利好，包括将“适度超前”加快建设数字基础设施，大力发展产业互联网平台，支持数据交易所建设，推进数据资源整合和开放共享等，持续激发数字经济发展潜能。围绕进一步做强做优做大我国数字经济，更多支持举措将进一步发力。国家发展改革委副主任林念修表示，下一步将适度超前部署建设新型基础设施，推进光纤网络扩容提速，5G规模部署和融合应用，加快传统基础设施数字化改造。深入推进“东数西算”工程，抓紧在全国建设10个数据中心集群。（经参）",
            "date_modified": "2022-05-26T22:34:22.000Z"
        },
        {
            "id": 2685508,
            "content_html": "",
            "url": "https://finance.sina.cn/7x24/2022-05-27/detail-imizirau5021701.d.html",
            "title": "  【得州小学枪击事件发生后 美全国步枪协会仍坚持举办枪支行业营销活动】尽管得州罗布小学枪击事件震惊全美，美国全国步枪协会（National Rifle Association of America）仍坚持于当地时间5月27日在休斯敦举行为期三天的枪支行业营销活动。美国全国步枪协会董事会成员菲尔·崔奇（Phil Travely）称，他不会支持禁止或限制获得枪支。他认为，重点应该放在更好的精神卫生保健上，并努力防止枪支暴力。",
            "date_modified": "2022-05-26T22:33:26.000Z"
        },
        {
            "id": 2685507,
            "content_html": "",
            "url": "https://finance.sina.cn/7x24/2022-05-27/detail-imizirau5021512.d.html",
            "title": "  【低买高卖，逾200亿资金“出走”宽基ETF】 随着市场近期震荡回暖，作为投资“风向标”，ETF成为各路资金的聚焦所在。在经过一段时间的持续抄底后，近一个月以来，超200亿元资金选择落袋为安，部分宽基ETF被大举净卖出。同时，前期跌幅较多的行业类、主题类ETF获得资金加仓。业内人士认为，ETF的资金进出具有一定参考意义，该市场参与者需求多元，既有长期配置资金，也有波段资金运作，A股指数投资趋势长期向好。（中证报）",
            "date_modified": "2022-05-26T22:31:35.000Z"
        },
        {
            "id": 2685506,
            "content_html": "",
            "url": "https://finance.sina.cn/7x24/2022-05-27/detail-imizmscu3609166.d.html",
            "title": "【日内请重点关注事项（以下均为北京时间）】① 07:30 日本5月东京CPI；② 09:30 中国4月规模以上工业企业利润、澳大利亚4月零售销售；③ 时间待定 中国移动通信联合会元宇宙产业委员会在京召开“2022元宇宙共识大会”；④ 16:00 欧元区4月M3货币供应；⑤ 时间待定 拼多多、搜狗、蘑菇街发布业绩报告，拼多多分析师电话会议安排在19:30；⑥ 19:35 欧洲央行首席经济学家连恩在2022年日本央行-IMES会议参加小组讨论；⑦ 20:30 美国4月个人收入、个人消费支出(PCE)、商品贸易帐；⑧ 22:00 美国5月密歇根大学消费者信心指数终值；⑨ 次日01:00 美国5月27日当周石油钻井数；⑩ 次日03:30 美国商品期货交易委员会（CFTC）公布周度持仓报告。",
            "date_modified": "2022-05-26T22:30:59.000Z"
        },
        {
            "id": 2685505,
            "content_html": "",
            "url": "https://finance.sina.cn/7x24/2022-05-27/detail-imizirau5021360.d.html",
            "title": "【债券基金火热“B面”：正视债市潜在风险】2022年以来，权益市场大幅波动，债券基金备受投资者青睐。中国证券报记者注意到，债券基金的发行较为火热，从发行份额看，债券基金占发行市场比例超过80%。近期多只提前结束募集的产品中，短债基金和中长期纯债基金超过七成。发行火热的背后，潜在风险可能正在集聚。不少基金人士提醒，从历史数据来看，超宽松资金面持续时间不会很长，债券市场的调整风险不容忽视。",
            "date_modified": "2022-05-26T22:29:48.000Z"
        },
        {
            "id": 2685504,
            "content_html": "",
            "url": "https://finance.sina.cn/7x24/2022-05-27/detail-imizmscu3608943.d.html",
            "title": "【美国累计新冠肺炎确诊病例超8381万例 】当地时间5月26日，根据美国约翰斯·霍普金斯大学（JHU）数据，截至美东时间当天17时21分（北京时间5月27日凌晨5时21分），美国累计新冠肺炎确诊病例达83811522例，累计死亡病例达1004084例。",
            "date_modified": "2022-05-26T22:28:31.000Z"
        },
        {
            "id": 2685503,
            "content_html": "",
            "url": "https://finance.sina.cn/7x24/2022-05-27/detail-imizmscu3608834.d.html",
            "title": "  莫德纳（MRNA）考虑2022年秋季向日本供应针对新冠肺炎变异毒株的疫苗。",
            "date_modified": "2022-05-26T22:27:06.000Z"
        },
        {
            "id": 2685502,
            "content_html": "",
            "url": "https://finance.sina.cn/7x24/2022-05-27/detail-imizirau5020812.d.html",
            "title": "【中宣部部长黄坤明：抓住战略机遇，推动数字经济高质量发展】2022中国国际大数据产业博览会26日在贵州贵阳举行，中共中央政治局委员、中宣部部长黄坤明以视频方式出席开幕式并讲话。黄坤明指出，新时代新征程上，数字经济前景广阔、大有可为。要激活数据要素价值，以实际应用需求为导向，强化高质量数据要素供给，全面深化重点产业、重点企业全链条数字化转型，推动数字经济和实体经济融合发展。要树立利民惠民导向，提高公共服务数字化水平，完善数字经济治理体系，全面提升数字生态治理能力，让人民群众更好享有数字化红利。要坚持互利共赢，拓展国际合作，构建网络空间命运共同体，以共商共建共享推动数字经济更好造福世界人民。（经参）",
            "date_modified": "2022-05-26T22:23:26.000Z"
        },
        {
            "id": 2685501,
            "content_html": "",
            "url": "https://finance.sina.cn/7x24/2022-05-27/detail-imizmscu3608171.d.html",
            "title": "  【A股锁价定增渐多 国资战投成为主力】A股再融资新规发布至今已经有两年多时间，上市公司通过定增引入战略投资者的成功案例逐渐增多。梳理近两年来再融资成功和失败案例发现，战投锁价定增出现两个趋势，一是战略投资者多为业内的龙头企业；二是具有国资背景的战投逐渐成为主角。数据显示，自2021年以来，新增预案中超八成战略投资者为国资企业。",
            "date_modified": "2022-05-26T22:19:50.000Z"
        },
        {
            "id": 2685500,
            "content_html": "",
            "url": "https://finance.sina.cn/7x24/2022-05-27/detail-imizmscu3608063.d.html",
            "title": "【布基纳法索发生袭击事件致50多人死亡】布基纳法索地方官员26日说，东部大区25日发生武装分子袭击事件，导致50多人死亡。布基纳法索东部大区区长亚梅奥果26日在一份声明中说，该大区马乔阿里镇的居民25日在前往帕马镇途中遭到不明身份武装分子袭击，造成50多人丧生。目前尚无任何组织宣称制造了这起袭击事件。（央视）",
            "date_modified": "2022-05-26T22:18:23.000Z"
        },
        {
            "id": 2685499,
            "content_html": "",
            "url": "https://finance.sina.cn/7x24/2022-05-27/detail-imizirau5020187.d.html",
            "title": "日本下周将探讨应对能源供应紧张的措施。",
            "date_modified": "2022-05-26T22:16:28.000Z"
        },
        {
            "id": 2685498,
            "content_html": "",
            "url": "https://finance.sina.cn/7x24/2022-05-27/detail-imizirau5020151.d.html",
            "title": "市场资讯：石油巨头雪佛龙与工会签署临时协议以结束加州炼油厂罢工。",
            "date_modified": "2022-05-26T22:16:09.000Z"
        },
        {
            "id": 2685497,
            "content_html": "",
            "url": "https://finance.sina.cn/7x24/2022-05-27/detail-imizirau5019936.d.html",
            "title": "  【百亿大项目接二连三，锂电产业链今年投资额已超6000亿】今年以来，已有60多家企业宣布了锂电产业链的投资计划。据不完全统计，今年锂电产业链新增规划投资已超过6000亿元，不少项目成为各地稳投资的关键力量。赛迪顾问锂电产业高级分析师赵丹桂表示，中长期来看，这是一个确定具有高成长空间的赛道，新能源汽车及储能市场的繁荣以及消费电子市场的稳定增长，催生了锂电池投资热潮，上下游扩产潮涌起，预计还将持续较长一段时间。（上证报）",
            "date_modified": "2022-05-26T22:13:24.000Z"
        },
        {
            "id": 2685496,
            "content_html": "",
            "title": "【央行：持续增加普惠小微贷款投放】人民银行近日印发《关于推动建立金融服务小微企业敢贷愿贷能贷会贷长效机制的通知》，从制约金融机构放贷的因素入手，按照市场化原则，进一步深化小微企业金融服务供给侧结构性改革，加快建立长效机制，着力提升金融机构服务小微企业的意愿、能力和可持续性。《通知》提出，发挥好货币政策工具总量和结构双重功能，用好降准、再贷款再贴现、普惠小微贷款支持工具，持续增加普惠小微贷款投放。",
            "date_modified": "2022-05-26T22:12:01.000Z"
        },
        {
            "id": 2685495,
            "content_html": "",
            "url": "https://finance.sina.cn/7x24/2022-05-27/detail-imizmscu3607387.d.html",
            "title": "【美联储6月加息50个基点的概率为92.9%】据CME“美联储观察”：美联储到6月份加息25个基点的概率为0%，加息50个基点的概率为92.9%，加息75个基点的概率为7.1%；到7月份累计加息25、50个基点的概率均为0%，累计加息75个基点的概率为5.3%，累计加息100个基点的概率为88.0%，累计加息125个基点的概率为6.7%。",
            "date_modified": "2022-05-26T22:10:59.000Z"
        },
        {
            "id": 2685494,
            "content_html": "",
            "url": "https://finance.sina.cn/7x24/2022-05-27/detail-imizmscu3606795.d.html",
            "title": "智利总统将在访美期间会见拜登。",
            "date_modified": "2022-05-26T22:05:41.000Z"
        },
        {
            "id": 2685493,
            "content_html": "",
            "url": "https://finance.sina.cn/7x24/2022-05-27/detail-imizmscu3606763.d.html",
            "title": "新西兰建议为最易感人群接种第二针新冠疫苗加强针。",
            "date_modified": "2022-05-26T22:05:19.000Z"
        },
        {
            "id": 2685492,
            "content_html": "",
            "url": "https://finance.sina.cn/7x24/2022-05-27/detail-imizirau5019072.d.html",
            "title": "美国总统拜登将于当地时间周五上午10点（北京时间晚上10点）在美国海军学院毕业典礼上发表演讲。",
            "date_modified": "2022-05-26T22:05:10.000Z"
        },
        {
            "id": 2685491,
            "content_html": "",
            "url": "https://finance.sina.cn/7x24/2022-05-27/detail-imizirau5018982.d.html",
            "title": "媒体消息：七国集团能源部长对俄罗斯问题表示强烈担忧。",
            "date_modified": "2022-05-26T22:04:12.000Z"
        },
        {
            "id": 2685490,
            "content_html": "",
            "url": "https://finance.sina.cn/7x24/2022-05-27/detail-imizmscu3606451.d.html",
            "title": "  【多重利好改善房地产市场融资预期 个别企业中期票据发行利率降至2.88%】随着近期利好政策不断叠加，房企融资市场显露回暖迹象。一方面，5月份以来，多家房企陆续开展债券融资；另一方面，房企融资利率较去年同期有所下降，个别房企中期票据发行利率甚至降至2.88%。从房企已经或准备在银行间市场发行的中期票据情况来看，业内人士认为，房地产市场的合理融资需求将继续得到满足，房企发行中期票据的规模有望进一步扩大。 (证券日报)",
            "date_modified": "2022-05-26T22:02:33.000Z"
        },
        {
            "id": 2685489,
            "content_html": "",
            "url": "https://finance.sina.cn/7x24/2022-05-27/detail-imizmscu3606362.d.html",
            "title": "【政策力挺“钱”路广，基建投资后劲足】经济下行压力的持续加大，表明发挥基础设施建设对支撑经济平稳增长的重要性也愈发凸显。随着近期顶层会议对基建投资持续关注以及部署安排，下半年基建投资的空间与资金来源也逐渐得以明确。专家表示，当前，我国基建项目储备充足，并获得政策层面力挺。从资金层面看，基建投资资金渠道广阔。以专项债为主的财政资金将在下半年持续形成实物工作量，货币政策将提供配套中长期资金，而REITs（不动产投资信托基金）、PPP（政府和社会资本合作）等手段也能进一步拓宽资金来源。基建投资有能力保持后劲，为稳增长提供关键支撑。（证券时报）",
            "date_modified": "2022-05-26T22:01:53.000Z"
        },
        {
            "id": 2685488,
            "content_html": "",
            "url": "https://finance.sina.cn/7x24/2022-05-27/detail-imizirau5018518.d.html",
            "title": "  周五（5月27日）亚太盘初，纳斯达克100股指期货跌0.2%。",
            "date_modified": "2022-05-26T22:01:30.000Z"
        },
        {
            "id": 2685487,
            "content_html": "",
            "url": "https://finance.sina.cn/7x24/2022-05-27/detail-imizirau5018437.d.html",
            "title": "  戴尔：预计第二季度营收在261-271亿美元之间。",
            "date_modified": "2022-05-26T22:00:40.000Z"
        },
        {
            "id": 2685486,
            "content_html": "",
            "url": "https://finance.sina.cn/7x24/2022-05-27/detail-imizirau5018390.d.html",
            "title": "俄罗斯外长拉夫罗夫：泽连斯基为恢复与俄罗斯的谈判以及与俄罗斯总统普京的会晤提出了不严肃的条件。",
            "date_modified": "2022-05-26T22:00:07.000Z"
        },
        {
            "id": 2685485,
            "content_html": "",
            "url": "https://finance.sina.cn/7x24/2022-05-27/detail-imizirau5018121.d.html",
            "title": "  【涉信披违法违规罚单显著增多 专家建议三方面着手提高信披质量】截至5月26日，年内交易所对上市公司以及相关主体（包括公司和个人）采取监管措施1153家次，涉及信披违法违规743家次，占比64.4%，同比增长49.2%。川财证券首席经济学家、研究所所长陈雳表示，提高信披质量可从多方面入手。首先，外部监管部门应不断细化信息披露指引，不断明确应当及时披露的事项，并依据指引从严监督。其次，中介机构也应当承担起相应责任，对企业进行积极引导，及时完成信披工作。最后，针对控股股东，则应加大监管力度，避免大股东滥用权利，影响信息披露质量及有效性。 (证券日报)",
            "date_modified": "2022-05-26T21:56:52.000Z"
        },
        {
            "id": 2685484,
            "content_html": "",
            "url": "https://finance.sina.cn/7x24/2022-05-27/detail-imizirau5017851.d.html",
            "title": "【证券时报头版：金融机构火速落实精神，6月信贷放量可期】自人民银行一天两场会议要求金融机构加大对实体经济的信贷支持后，银行近日也在内部抓紧部署落实。记者近日从多位银行业人士了解到，多家银行内部开会向各级分支机构部署落实，预计6月新增信贷投放有望有所好转。当前实体经济有效融资需求不足的问题仍未得到明显改善，有分析人士认为，新增信贷投放短期内可通过票据融资、政策性银行加大贷款投放力度等手段维持一定水平，但有效融资需求的激发仍离不开经济体系的顺畅运行。德意志银行大中华区宏观策略主管刘立男表示，下阶段基础设施建设、绿色发展预计会是信贷投放的主力方向，6月新增信贷有望明显反弹。",
            "date_modified": "2022-05-26T21:54:36.000Z"
        },
        {
            "id": 2685483,
            "content_html": "",
            "url": "https://finance.sina.cn/7x24/2022-05-27/detail-imizmscu3604768.d.html",
            "title": "【巴克莱：中期看好瑞郎】因市场情绪仍不稳定，且考虑到全球通胀粘性，瑞士央行干预的可能性较小，我们预计瑞郎将继续维持在其历史强区间。瑞士央行最近的鹰派言论也有助于缩小瑞郎与G10其他成员国之间的汇率差。瑞士央行行长乔丹指出了可能面临“第二轮”效应的风险，并承诺保持价格稳定，并在通胀风险出现时采取行动。",
            "date_modified": "2022-05-26T21:46:19.000Z"
        },
        {
            "id": 2685482,
            "content_html": "",
            "url": "https://finance.sina.cn/7x24/2022-05-27/detail-imizmscu3604699.d.html",
            "title": "  戴尔：由于目前需求和全行业供应链面临挑战，预计（订单）积压量至少在第二季度还会保持较高水平。",
            "date_modified": "2022-05-26T21:45:27.000Z"
        },
        {
            "id": 2685481,
            "content_html": "",
            "url": "https://finance.sina.cn/7x24/2022-05-27/detail-imizmscu3604421.d.html",
            "title": "  戴尔：预计第二季度零部件成本将出现通胀，而物流成本仍将处于高位。",
            "date_modified": "2022-05-26T21:44:08.000Z"
        },
        {
            "id": 2685480,
            "content_html": "",
            "url": "https://finance.sina.cn/7x24/2022-05-27/detail-imizirau5016665.d.html",
            "title": "戴尔：第一季度主要商品成本出现通缩，但物流支出仍居高不下。",
            "date_modified": "2022-05-26T21:43:27.000Z"
        },
        {
            "id": 2685479,
            "content_html": "",
            "url": "https://finance.sina.cn/7x24/2022-05-27/detail-imizmscu3604071.d.html",
            "title": "  【荔枝第一季度营收5.167亿元 同比扭亏为盈】荔枝公布2022财年第一季度未经审计财报。报告显示，荔枝第一季度净营收为5.167亿元人民币（约合8150万美元），同比增长4%；净利润为1640万元人民币（约合260万美元），相比之下去年同期的净亏损为7000万元人民币，同比扭亏为盈。",
            "date_modified": "2022-05-26T21:41:29.000Z"
        },
        {
            "id": 2685478,
            "content_html": "",
            "url": "https://finance.sina.cn/7x24/2022-05-27/detail-imizmscu3603901.d.html",
            "title": "【新增专项债5月份发行或创年内新高，有力发挥经济增长托底作用】5月份新增专项债发行节奏明显加快。据统计，截至5月26日，年内新增专项债发行规模达18200.63亿元，其中5月1日至5月26日发行规模达4181.73亿元。根据地方债信披文件，5月份新增专项债发行规模将达到6319.62亿元，将创年内新高。东方金诚研究发展部高级分析师冯琳表示，将专项债支持范围扩大到新基建领域后，预计专项债对新基建的支持力度会明显加大。新增专项债或于6月底前“基本发完”，预计二季度发行量将达到1.8万亿元至2万亿元。（证券日报）",
            "date_modified": "2022-05-26T21:39:24.000Z"
        },
        {
            "id": 2685477,
            "content_html": "",
            "url": "https://finance.sina.cn/7x24/2022-05-27/detail-imizmscu3603714.d.html",
            "title": "  【德国海军护卫舰启航参与北约北翼的防御任务】德国F123型护卫舰“梅克伦堡-前波莫瑞号”离开威廉港，前往参与北约北翼的防御任务。据德国海军司令部介绍，“梅克伦堡-前波莫瑞号”将在未来几个月加入北约快速反应部队，帮助协防北约北翼。“梅克伦堡-前波莫瑞号”舰长约140米，配备两架舰载直升机。舰上有220名士兵，其中包括一支医疗专家小组和海军航空兵。",
            "date_modified": "2022-05-26T21:37:36.000Z"
        },
        {
            "id": 2685476,
            "content_html": "",
            "url": "https://finance.sina.cn/7x24/2022-05-27/detail-imizirau5016061.d.html",
            "title": "媒体消息：美国可能在下周宣布新的乌克兰安全援助计划。",
            "date_modified": "2022-05-26T21:36:54.000Z"
        },
        {
            "id": 2685475,
            "content_html": "",
            "url": "https://finance.sina.cn/7x24/2022-05-27/detail-imizirau5015849.d.html",
            "title": "【摩洛哥将延长国家紧急状态至6月底】摩洛哥政府当地时间26日宣布，将目前因抗击新冠疫情而实行的国家紧急状态延长至6月底。近期，摩洛哥新冠疫情有升温迹象，日平均新增确诊病例从以前的50例左右增至200例左右。摩卫生部将其归因于民众放松对疫情的警惕、未能严格遵守相关防疫措施所致。（央视）",
            "date_modified": "2022-05-26T21:34:44.000Z"
        },
        {
            "id": 2685474,
            "content_html": "",
            "url": "https://finance.sina.cn/7x24/2022-05-27/detail-imizirau5015724.d.html",
            "title": "【白宫新闻秘书：美国的枪支比美国人口还多】当地时间5月26日，美国白宫新闻秘书卡琳·让-皮埃尔在简报会上表示，美国的枪支比美国人口还多，枪支暴力正在摧毁美国家庭和社区。",
            "date_modified": "2022-05-26T21:33:18.000Z"
        },
        {
            "id": 2685473,
            "content_html": "",
            "url": "https://finance.sina.cn/7x24/2022-05-27/detail-imizirau5015266.d.html",
            "title": "俄罗斯副总理尤里·鲍里索夫表示，俄罗斯如今在石油天然气出口问题上着眼于东方，致力于开拓亚洲市场。",
            "date_modified": "2022-05-26T21:28:01.000Z"
        },
        {
            "id": 2685472,
            "content_html": "",
            "url": "https://finance.sina.cn/7x24/2022-05-27/detail-imizmscu3602649.d.html",
            "title": "【美国债市：国债涨跌互见 在强劲的7年期国债发行后维持趋陡】美国国债涨跌互现，收益率曲线围绕基本持平的7年期收益率扭转趋陡，短期债跑赢长期债。到下午，趋陡幅度有所收窄，但在强劲的7年期国债招标带来历史最低的一级交易商得标比例后，5s30s当天仍扩大超过2个基点。在美国早盘，股市上涨，给收益率带来了上行压力；期货大宗交易引起了长期收益率的波动，其中包括超长期国债期货的大宗卖单，和130万美元/基点价值的曲线趋平交易。在曲线整个前端，投资者正在考虑美联储9月暂停加息或将加息步伐降至25个基点的可能性。",
            "date_modified": "2022-05-26T21:25:28.000Z"
        },
        {
            "id": 2685471,
            "content_html": "",
            "url": "https://finance.sina.cn/7x24/2022-05-27/detail-imizmscu3602610.d.html",
            "title": "周四（5月26日）纽约尾盘，美国10年期基准国债收益率涨0.18个基点，报2.7469%，盘中交投于2.7023%-2.7954%区间。",
            "date_modified": "2022-05-26T21:24:58.000Z"
        },
        {
            "id": 2685470,
            "content_html": "",
            "url": "https://finance.sina.cn/7x24/2022-05-27/detail-imizirau5014844.d.html",
            "title": "  周四（5月26日）纽约尾盘，CME比特币期货BTC主力合约报29420美元，较周三纽约尾盘跌0.39%，盘中交投于29895-27995美元区间。CME以太币期货DCR主力合约报1825.50美元，较周三跌7.29%，盘中交投于1976.00-1728.50美元区间。",
            "date_modified": "2022-05-26T21:22:42.000Z"
        },
        {
            "id": 2685469,
            "content_html": "",
            "url": "https://finance.sina.cn/7x24/2022-05-27/detail-imizmscu3602304.d.html",
            "title": "离岸人民币（CNH）兑美元北京时间04:59报6.7674元，较周三纽约尾盘跌547点，盘中整体交投于6.7013-6.7719元区间。",
            "date_modified": "2022-05-26T21:21:19.000Z"
        },
        {
            "id": 2685468,
            "content_html": "",
            "url": "https://finance.sina.cn/7x24/2022-05-27/detail-imizmscu3602285.d.html",
            "title": "纽交所ARCA钢铁指数收涨2.70%，报1831.49点。",
            "date_modified": "2022-05-26T21:21:06.000Z"
        },
        {
            "id": 2685467,
            "content_html": "",
            "url": "https://finance.sina.cn/7x24/2022-05-27/detail-imizirau5014686.d.html",
            "title": "加拿大标普/TSX综合指数收涨0.73%，报20532.18点。巴西圣保罗证交所指数收涨1.18%，报11.2万点。",
            "date_modified": "2022-05-26T21:20:53.000Z"
        },
        {
            "id": 2685466,
            "content_html": "",
            "url": "https://finance.sina.cn/7x24/2022-05-27/detail-imizirau5014300.d.html",
            "title": "  好市多高级财务副总裁：现在不是上调会员费的合适时候。对于能够将更高成本转嫁出去感到满意。",
            "date_modified": "2022-05-26T21:16:37.000Z"
        },
        {
            "id": 2685465,
            "content_html": "",
            "title": "机构调查：预计新西兰房价2022年下跌9.0%，2023年跌2.0%（2月调查为跌0.8%和涨1.5%）。",
            "date_modified": "2022-05-26T21:14:28.000Z"
        },
        {
            "id": 2685464,
            "content_html": "",
            "url": "https://finance.sina.cn/7x24/2022-05-27/detail-imizmscu3601515.d.html",
            "title": "新西兰总理阿德恩：将于周二在白宫与美国总统拜登会面。",
            "date_modified": "2022-05-26T21:12:38.000Z"
        },
        {
            "id": 2685463,
            "content_html": "",
            "url": "https://finance.sina.cn/7x24/2022-05-27/detail-imizirau5013814.d.html",
            "title": "全球最大白银ETF--iShares Silver Trust持仓较上日减少86.12吨，当前持仓量为17357.96吨。",
            "date_modified": "2022-05-26T21:10:47.000Z"
        },
        {
            "id": 2685462,
            "content_html": "",
            "url": "https://finance.sina.cn/7x24/2022-05-27/detail-imizmscu3601354.d.html",
            "title": "【乌媒：安-225运输机残骸被乌方从戈斯托梅利机场拖走】当地时间26日，乌克兰媒体发布视频称，安-225运输机残骸被乌方从戈斯托梅利机场拖走。乌克兰总统泽连斯基此前曾表示，计划筹集8亿美元建造第二架安-225。（央视）",
            "date_modified": "2022-05-26T21:10:03.000Z"
        },
        {
            "id": 2685461,
            "content_html": "",
            "url": "https://finance.sina.cn/7x24/2022-05-27/detail-imizirau5013728.d.html",
            "title": "  【CleverTap：印度电子商务使用量女性占54%】CleverTap的调查揭示了印度移动应用市场的机遇。印度女性占全国应用总使用量的28%，在农村这个数字是16.4%。它们共同推动了超过70%的购买决策。印度女性电子商务应用使用量超过男性，占54%。",
            "date_modified": "2022-05-26T21:09:41.000Z"
        },
        {
            "id": 2685460,
            "content_html": "",
            "url": "https://finance.sina.cn/7x24/2022-05-27/detail-imizirau5013455.d.html",
            "title": "  【投资端低迷加大利差损风险 专家建议险企摒弃定价竞争】“一季度的投资收益率将保险业拉回了现实。”一位业内人士如此评价一季度保险业的成绩。惨淡的投资收益率也让保险公司面临的利差损风险进一步加大。为应对利差损风险，部分险企持续下调万能险结算利率。同时，业内人士认为，尽量避免纯粹的定价竞争，寻求差异化策略，也是险企防范利差损的重要举措。",
            "date_modified": "2022-05-26T21:06:00.000Z"
        },
        {
            "id": 2685459,
            "content_html": "",
            "title": "  中国地震台网正式测定：05月27日04时51分在新疆昌吉州昌吉市（北纬43.59度，东经86.58度）发生3.1级地震，震源深度18千米。",
            "date_modified": "2022-05-26T21:02:12.000Z"
        },
        {
            "id": 2685458,
            "content_html": "",
            "url": "https://finance.sina.cn/7x24/2022-05-27/detail-imizirau5013099.d.html",
            "title": "市场资讯： 拉美加密数字货币交易所Bitso裁员80人。",
            "date_modified": "2022-05-26T21:02:07.000Z"
        },
        {
            "id": 2685457,
            "content_html": "",
            "url": "https://finance.sina.cn/7x24/2022-05-27/detail-imizirau5012964.d.html",
            "title": "【芝加哥大豆期货周四涨超2%，巴西干旱天气推动阿拉比卡咖啡期货涨超4%】 周四（5月26日）纽约尾盘，CBOT玉米期货跌1.13%，报7.63-1/2美元/蒲式耳，5月6日以来持续走低，脱离4月29日顶部8.24-1/2美元。 CBOT小麦期货跌0.59%，报11.42美元/蒲式耳。 CBOT大豆期货涨2.74%，报17.25-3/4美元/蒲式耳，豆粕期货涨约1.16%，豆油期货涨约1.90%。 CBOT软木期货涨4.37%，报680.30美元/1000板英尺，5月24日曾走软至636.30美元——跌向2021年9月2日低点594.40美元。 CBOT瘦肉猪期货涨3.54%，活牛期货涨约0.20%，饲牛期货跌0.80%。 ICE原糖期货跌0.76%，ICE白糖期货涨0.07%。 ICE阿拉比卡咖啡期货涨4.03%，大体上守住纽约中午录得的顶部227.30美分，投资者担心干旱天气可能会伤害到巴西局部地区的产量；罗布斯塔咖啡期货跌0.26%。 ICE棉花期货跌3.18%。",
            "date_modified": "2022-05-26T21:00:25.000Z"
        },
        {
            "id": 2685456,
            "content_html": "",
            "url": "https://finance.sina.cn/7x24/2022-05-27/detail-imizmscu3600316.d.html",
            "title": "美国白宫：正考虑扩大美洲峰会的邀请范围。",
            "date_modified": "2022-05-26T20:55:52.000Z"
        },
        {
            "id": 2685455,
            "content_html": "",
            "url": "https://finance.sina.cn/7x24/2022-05-27/detail-imizirau5012310.d.html",
            "title": "美股大类资产类ETF周四多数收涨，纳指100ETF涨超2.7表现最好，美国布伦特原油基金（BNO）、罗素2000指数ETF涨超2.2%，标普500ETF涨2%，大豆基金涨超1.8%，道指ETF、新兴市场ETF涨超1.5%，农产品基金涨1%，欧元做多涨超0.4%，美国房地产ETF涨超0.1%。恐慌指数做多跌超1.6%表现最差，美国国债20+年ETF跌超0.4%，黄金ETF跌近0.2%。",
            "date_modified": "2022-05-26T20:51:39.000Z"
        },
        {
            "id": 2685454,
            "content_html": "",
            "url": "https://finance.sina.cn/7x24/2022-05-27/detail-imizirau5012267.d.html",
            "title": "美国白宫：没有人讨论为了获得粮食出口而放松对俄罗斯的制裁。",
            "date_modified": "2022-05-26T20:51:06.000Z"
        },
        {
            "id": 2685453,
            "content_html": "",
            "url": "https://finance.sina.cn/7x24/2022-05-27/detail-imizirau5011959.d.html",
            "title": "穆迪：负面展望反映出埃及对冲外部冲击能力减弱的风险不断上升。",
            "date_modified": "2022-05-26T20:46:35.000Z"
        },
        {
            "id": 2685452,
            "content_html": "",
            "url": "https://finance.sina.cn/7x24/2022-05-27/detail-imizmscu3599475.d.html",
            "title": "穆迪：确认埃及“B2”评级，前景展望下调至负面。",
            "date_modified": "2022-05-26T20:44:13.000Z"
        },
        {
            "id": 2685451,
            "content_html": "",
            "url": "https://finance.sina.cn/7x24/2022-05-27/detail-imizirau5011770.d.html",
            "title": "  【加拿大安大略省确诊首例猴痘感染病例】加拿大安大略省省会多伦多的公共卫生局表示，该省已经确诊首例猴痘感染病例。至此，加拿大境内的猴痘感染病例已经增至26例，其余25例均在东部邻省魁北克省境内。多伦多公共卫生局说，该病患目前病情稳定，正在医院恢复。卫生局没有公布更多的信息。",
            "date_modified": "2022-05-26T20:43:59.000Z"
        },
        {
            "id": 2685450,
            "content_html": "",
            "url": "https://finance.sina.cn/7x24/2022-05-27/detail-imizmscu3599370.d.html",
            "title": "  沙特外交部官员：伊朗需要为未来的合作建立信任，有一些问题可以讨论，以缓解该地区的紧张局势。",
            "date_modified": "2022-05-26T20:42:46.000Z"
        },
        {
            "id": 2685449,
            "content_html": "",
            "url": "https://finance.sina.cn/7x24/2022-05-27/detail-imizmscu3599347.d.html",
            "title": "【白俄罗斯计划成立南方作战司令部】白俄罗斯总统卢卡申科26日表示，白俄罗斯计划成立南方作战司令部。卢卡申科说，以美国为首的西方国家继续奉行令世界局势恶化的政策，它们与俄罗斯等国激烈对抗并在白俄罗斯周边举行大规模军事演习。白邻国发生的事件表明，白俄罗斯军事安全面临的威胁发生巨大变化。卢卡申科表示，当前局势比以往任何时候更需要白俄罗斯部队随时做好准备，对军事侵犯行为做出充分反应。（央视）",
            "date_modified": "2022-05-26T20:42:21.000Z"
        },
        {
            "id": 2685448,
            "content_html": "",
            "url": "https://finance.sina.cn/7x24/2022-05-27/detail-imizmscu3599303.d.html",
            "title": "  沙特外交部官员：在可预见的未来，沙特和伊朗外长之间没有安排会晤。",
            "date_modified": "2022-05-26T20:41:42.000Z"
        },
        {
            "id": 2685447,
            "content_html": "",
            "url": "https://finance.sina.cn/7x24/2022-05-27/detail-imizmscu3599282.d.html",
            "title": "美股行业ETF周四全线收涨，全球航空业ETF涨超5.1%表现最好，可选消费ETF涨4.9%，网络股指数ETF涨超2.7%，科技行业ETF、银行业ETF、金融业ETF涨超2.3%，全球科技股指数ETF涨超2.1%，能源业ETF、日常消费品ETF涨超1%，生物科技指数ETF涨0.9%，医疗业ETF涨超0.4%，公用事业ETF涨近0.3%。",
            "date_modified": "2022-05-26T20:41:18.000Z"
        },
        {
            "id": 2685446,
            "content_html": "",
            "url": "https://finance.sina.cn/7x24/2022-05-27/detail-imizirau5011079.d.html",
            "title": "  BOK Financial高级交易副总裁Dennis Kissler：人们意识到供应将继续萎缩，这就是推动原油价格走高的原因。",
            "date_modified": "2022-05-26T20:35:27.000Z"
        },
        {
            "id": 2685445,
            "content_html": "",
            "url": "https://finance.sina.cn/7x24/2022-05-27/detail-imizirau5010945.d.html",
            "title": "  【美国银行：美联储晚些时候或暂停升息 意味中长期收益率见顶】美国银行表示，美联储官员最新政策言论为交易员提供了押注7月后暂停加息的机会。Ralph Axel和Bruno Braizinha在报告中表示，克利夫兰联储行长Loretta Mester、亚特兰大联储行长Raphael Bostic过去两周的讲话令人意识到金融市场环境可能推动美联储在9月份放慢，甚至停止升息步伐。这对隔夜指数掉期利率及5年期利率都产生了影响。",
            "date_modified": "2022-05-26T20:33:48.000Z"
        },
        {
            "id": 2685444,
            "content_html": "",
            "url": "https://finance.sina.cn/7x24/2022-05-27/detail-imizmscu3598551.d.html",
            "title": "  标普500指数的11个板块周四普遍收涨，可选消费板块涨约4.8%领跑——成分股Dollar Tree涨约21.9%、达乐公司（DG）涨超13.7%、挪威邮轮涨约12.1%、麦当劳涨约1.7%倒数第二、达美乐披萨（DPZ）涨超0.8%表现最差，信息技术板块涨超2.4%，金融板块涨超2.2%，通信板块涨超2.0%，房地产板块则跌0.1%是唯一收跌的板块。",
            "date_modified": "2022-05-26T20:33:01.000Z"
        },
        {
            "id": 2685443,
            "content_html": "",
            "url": "https://finance.sina.cn/7x24/2022-05-27/detail-imizirau5010763.d.html",
            "title": "美国至5月21日当周外国央行持有美国国债(亿美元)：前值 -113.37，公布 -41.72。",
            "date_modified": "2022-05-26T20:31:57.000Z"
        },
        {
            "id": 2685442,
            "content_html": "",
            "url": "https://finance.sina.cn/7x24/2022-05-27/detail-imizirau5010686.d.html",
            "title": "戴尔(DELL.N)2023财年Q1 EPS：前值$1.13，预期$1.18，公布$1.37。",
            "date_modified": "2022-05-26T20:30:45.000Z"
        },
        {
            "id": 2685441,
            "content_html": "",
            "url": "https://finance.sina.cn/7x24/2022-05-27/detail-imizirau5010595.d.html",
            "title": "戴尔(DELL.N)2023财年Q1净利润（亿美元）：前值8.85，预期7.28，公布10.72。",
            "date_modified": "2022-05-26T20:30:10.000Z"
        },
        {
            "id": 2685440,
            "content_html": "",
            "url": "https://finance.sina.cn/7x24/2022-05-27/detail-imizirau5010412.d.html",
            "title": "戴尔(DELL.N)2023财年Q1营收（亿美元）：前值244.99，预期250.43，公布261.2。",
            "date_modified": "2022-05-26T20:28:07.000Z"
        },
        {
            "id": 2685439,
            "content_html": "",
            "url": "https://finance.sina.cn/7x24/2022-05-27/detail-imizirau5010227.d.html",
            "title": "欧洲地中海地震中心（EMSC）：智利西部发生5.1级地震。",
            "date_modified": "2022-05-26T20:25:50.000Z"
        },
        {
            "id": 2685438,
            "content_html": "",
            "title": "【股市收盘】道琼斯指数5月26日（周四）收盘上涨516.91点，涨幅1.61%，报32637.19点；标普500指数5月26日（周四）收盘上涨79.11点，涨幅1.99%，报4057.84点；纳斯达克综合指数5月26日（周四）收盘上涨305.91点，涨幅2.68%，报11740.65点。",
            "date_modified": "2022-05-26T20:23:01.000Z"
        },
        {
            "id": 2685437,
            "content_html": "",
            "url": "https://finance.sina.cn/7x24/2022-05-27/detail-imizirau5009882.d.html",
            "title": "巴西最近24小时新增33,910例新冠肺炎病例，新增143例死亡病例。",
            "date_modified": "2022-05-26T20:21:22.000Z"
        },
        {
            "id": 2685436,
            "content_html": "",
            "url": "https://finance.sina.cn/7x24/2022-05-27/detail-imizirau5009863.d.html",
            "title": "  美国白宫：预计俄罗斯潜在违约对美国和全球经济影响很小。",
            "date_modified": "2022-05-26T20:21:11.000Z"
        },
        {
            "id": 2685435,
            "content_html": "",
            "url": "https://finance.sina.cn/7x24/2022-05-27/detail-imizirau5009647.d.html",
            "title": "GAP预计全年调整后每股收益0.3-0.6美元，此前预计为1.85-2.05美元，分析师预期为1.32美元。GAP美股盘后暴跌超15%。",
            "date_modified": "2022-05-26T20:18:20.000Z"
        },
        {
            "id": 2685434,
            "content_html": "",
            "url": "https://finance.sina.cn/7x24/2022-05-27/detail-imizirau5009581.d.html",
            "title": "好市多(COST.O)2022财年Q3 EPS：前值$2.75，预期$3.02，公布$3.04。",
            "date_modified": "2022-05-26T20:17:53.000Z"
        },
        {
            "id": 2685433,
            "content_html": "",
            "url": "https://finance.sina.cn/7x24/2022-05-27/detail-imizirau5009524.d.html",
            "title": " 好市多(COST.O)2022财年Q3 营收（亿美元）：前值452.77，预期517.07，公布526。",
            "date_modified": "2022-05-26T20:17:24.000Z"
        },
        {
            "id": 2685432,
            "content_html": "",
            "url": "https://finance.sina.cn/7x24/2022-05-27/detail-imizirau5009240.d.html",
            "title": "  热门中概股大涨，知乎涨超22%，阿里巴巴、百度涨超14%，蔚来涨近10%，拼多多涨超9%，爱奇艺、哔哩哔哩、理想汽车涨超8%，小鹏汽车涨超7%，英伟达、京东涨超5%。",
            "date_modified": "2022-05-26T20:14:57.000Z"
        },
        {
            "id": 2685431,
            "content_html": "",
            "url": "https://finance.sina.cn/7x24/2022-05-27/detail-imizmscu3596612.d.html",
            "title": "Farfetch(FTCH.N)2022年Q1 营收（亿美元）：前值4.85，预期5.62，公布5.15。",
            "date_modified": "2022-05-26T20:12:57.000Z"
        },
        {
            "id": 2685430,
            "content_html": "",
            "url": "https://finance.sina.cn/7x24/2022-05-27/detail-imizirau5008868.d.html",
            "title": "财报公布后，迈威尔科技盘后跌3%。",
            "date_modified": "2022-05-26T20:12:27.000Z"
        },
        {
            "id": 2685429,
            "content_html": "",
            "url": "https://finance.sina.cn/7x24/2022-05-27/detail-imizmscu3596488.d.html",
            "title": "迈威尔科技(MRVL.O)2023财年Q1 EPS：前值$-0.13，预期$0.05，公布$-0.2。",
            "date_modified": "2022-05-26T20:11:25.000Z"
        }
    ]
}